{
  "accentColor": "{{appsmith.theme.colors.primaryColor}}",
  "animateLoading": true,
  "borderRadius": "{{appsmith.theme.borderRadius.appBorderRadius}}",
  "bottomRow": 23,
  "boxShadow": "none",
  "closeOnSelection": true,
  "dateFormat": "MM-DD-YYYY",
  "datePickerType": "DATE_PICKER",
  "defaultDate": "2024-12-15T00:20:38.809Z",
  "dynamicBindingPathList": [
    {
      "key": "accentColor"
    },
    {
      "key": "borderRadius"
    }
  ],
  "dynamicHeight": "FIXED",
  "dynamicTriggerPathList": [],
  "firstDayOfWeek": 0,
  "isDisabled": false,
  "isLoading": false,
  "isRequired": false,
  "isVisible": true,
  "key": "xof5o7wf0c",
  "label": "Thời gian",
  "labelAlignment": "left",
  "labelPosition": "Top",
  "labelTextSize": "0.875rem",
  "labelWidth": 5,
  "leftColumn": 0,
  "maxDate": "2121-12-31T18:29:00.000Z",
  "maxDynamicHeight": 9000,
  "minDate": "1920-12-31T18:30:00.000Z",
  "minDynamicHeight": 4,
  "minWidth": 450,
  "mobileBottomRow": 24,
  "mobileLeftColumn": 35,
  "mobileRightColumn": 55,
  "mobileTopRow": 17,
  "needsErrorInfo": false,
  "parentColumnSpace": 6.53125,
  "parentId": "hkhjfptpn4",
  "parentRowSpace": 10,
  "renderMode": "CANVAS",
  "responsiveBehavior": "fill",
  "rightColumn": 17,
  "shortcuts": false,
  "timePrecision": "minute",
  "topRow": 16,
  "type": "DATE_PICKER_WIDGET2",
  "version": 2,
  "widgetId": "0r9u1gx4ko",
  "widgetName": "DatePicker1"
}